{
	"target": "$(ProgramPath)/resource/test_config.json",
	"targetType": "json",
	"widget":[
		{	
			"node": "Preference",
			"type": "Frame",
			"icon": "",
			"title": "i18n:YSS::config.preference.title",
			"text": "i18n:YSS::config.preference.text",
			"children":[
				{
					"node": "Language",
					"type": "ComboBox",
					"icon": "",
					"title": "i18n:YSS::config.language.title",
					"text": "i18n:YSS::config.language.text",
					"data": {
						
						"comboBox": [
							{
								"data": "zh_CN",
								"key": "i18n:YSS::config.language.zh_CN"
							},
							{
								"data": "en_US",
								"key": "i18n:YSS::config.language.en_US"
							}
						],
						"default": "zh_CN"
					}
				},
				{
					"node": "ReloadTab",
					"type": "RadioButton",
					"icon": "",
					"title": "i18n:YSS::config.reloadtab.title",
					"text": "i18n:YSS::config.reloadtab.text",
					"data": {
						"default": true
					}
				},
				{
					"node": "Theme",
					"type": "ComboBox",
					"icon": "",
					"title": "i18n:YSS::config.theme.title",
					"text": "i18n:YSS::config.theme.text",
					"data": {
						"comboBox": [
							{
								"data": "theme_dark",
								"key": "i18n:YSS::config.theme.dark"
							},
							{
								"data": "theme_light",
								"key": "i18n:YSS::config.theme.light"
							}
						],
						"default": "theme_dark"
					}
				}
			]	
		}
	]
}